trustedtwin/__init__.py
trustedtwin/tt_api.py
trustedtwin/tt_api.pyi
trustedtwin/tt_api_async.py
trustedtwin/tt_api_async.pyi
trustedtwin/tt_api_base.py
trustedtwin/tt_endpoints.py
trustedtwin-3.18.20241001204517.dist-info/LICENSE
trustedtwin-3.18.20241001204517.dist-info/METADATA
trustedtwin-3.18.20241001204517.dist-info/WHEEL
trustedtwin-3.18.20241001204517.dist-info/top_level.txt
trustedtwin-3.18.20241001204517.dist-info/RECORD
