Metadata-Version: 2.1
Name: trustedtwin
Version: 3.18.20241001204517
Summary: Trusted Twin Python client
Home-page: https://gitlab.com/trustedtwin/solutions/trustedtwin-python-client
Author: TrustedTwin
License: MIT
Requires-Python: >=3.9
License-File: LICENSE
Requires-Dist: requests>=2.30
Provides-Extra: async
Requires-Dist: requests>=2.30; extra == "async"
Requires-Dist: aiohttp<4,>=3.8; extra == "async"
